[{"Item Code": "000ECCED", "Item Name": "Emergency Power Cell", "Console Command": "player.additem 000ECCED 1"}, {"Item Code": "001336C1", "Item Name": "Chameleon armor mod (blends in with environment when crouched)", "Console Command": "player.additem 001336C1 1"}, {"Item Code": "002B559C", "Item Name": ".27 Caliber", "Console Command": "player.additem 002B559C 1"}, {"Item Code": "00228570", "Item Name": "Bounty Hunter Spacesuit", "Console Command": "player.additem 00228570 1"}, {"Item Code": "0004AD3E", "Item Name": "7.77MM Caseless", "Console Command": "player.additem 0004AD3E 1"}, {"Item Code": "002B4AFC", "Item Name": "15X25 CLL Shotgun Shell", "Console Command": "player.additem 002B4AFC 1"}, {"Item Code": "002B5598", "Item Name": ".45 Caliber ACP", "Console Command": "player.additem 002B5598 1"}, {"Item Code": "0003FB19", "Item Name": "Ship Spare Parts", "Console Command": "player.additem 0003FB19 1"}]